{
  "paper_size": "A5 (148x210mm)",
  "items": [
    {
      "type": "text",
      "id": "baslik",
      "x": 10,
      "y": 15,
      "text": "POS Sistemi",
      "font_family": "Tahoma",
      "font_size": 22,
      "font_bold": true,
      "color": "#000000",
      "text_width": 400,
      "text_height": 28,
      "text_align": "center"
    },
    {
      "type": "text",
      "id": "alt_baslik",
      "x": 10,
      "y": 45,
      "text": "Satış Fişi",
      "font_family": "Tahoma",
      "font_size": 14,
      "font_bold": false,
      "color": "#666666",
      "text_width": 400,
      "text_height": 20,
      "text_align": "center"
    },
    {
      "type": "shape",
      "id": "kutu_bilgi",
      "x": 10,
      "y": 75,
      "width": 400,
      "height": 80,
      "fill_color": "#f8f9fa",
      "border": {
        "sides": {
          "top": true,
          "bottom": true,
          "left": true,
          "right": true
        },
        "thickness": 1,
        "color": "#dee2e6"
      }
    },
    {
      "type": "text",
      "id": "bilgi_fis_no_label",
      "x": 20,
      "y": 82,
      "text": "Fiş No:",
      "font_family": "Tahoma",
      "font_size": 11,
      "font_bold": true,
      "color": "#000000",
      "text_width": 60,
      "text_height": 16,
      "text_align": "left"
    },
    {
      "type": "text",
      "id": "bilgi_fis_no_value",
      "x": 80,
      "y": 82,
      "text": "{{FIS_NO}}",
      "font_family": "Tahoma",
      "font_size": 11,
      "font_bold": false,
      "color": "#333333",
      "text_width": 150,
      "text_height": 16,
      "text_align": "left"
    },
    {
      "type": "text",
      "id": "bilgi_tarih_label",
      "x": 20,
      "y": 100,
      "text": "Tarih:",
      "font_family": "Tahoma",
      "font_size": 11,
      "font_bold": true,
      "color": "#000000",
      "text_width": 60,
      "text_height": 16,
      "text_align": "left"
    },
    {
      "type": "text",
      "id": "bilgi_tarih_value",
      "x": 80,
      "y": 100,
      "text": "{{TARIH}} {{SAAT}}",
      "font_family": "Tahoma",
      "font_size": 11,
      "font_bold": false,
      "color": "#333333",
      "text_width": 150,
      "text_height": 16,
      "text_align": "left"
    },
    {
      "type": "text",
      "id": "bilgi_musteri_label",
      "x": 20,
      "y": 118,
      "text": "Müşteri:",
      "font_family": "Tahoma",
      "font_size": 11,
      "font_bold": true,
      "color": "#000000",
      "text_width": 60,
      "text_height": 16,
      "text_align": "left"
    },
    {
      "type": "text",
      "id": "bilgi_musteri_value",
      "x": 80,
      "y": 118,
      "text": "{{MUSTERI_ADI}}",
      "font_family": "Tahoma",
      "font_size": 11,
      "font_bold": false,
      "color": "#333333",
      "text_width": 150,
      "text_height": 16,
      "text_align": "left"
    },
    {
      "type": "text",
      "id": "bilgi_odeme_label",
      "x": 20,
      "y": 136,
      "text": "Ödeme Tipi:",
      "font_family": "Tahoma",
      "font_size": 11,
      "font_bold": true,
      "color": "#000000",
      "text_width": 70,
      "text_height": 16,
      "text_align": "left"
    },
    {
      "type": "text",
      "id": "bilgi_odeme_value",
      "x": 90,
      "y": 136,
      "text": "{{ODEME_TIPI}}",
      "font_family": "Tahoma",
      "font_size": 11,
      "font_bold": false,
      "color": "#333333",
      "text_width": 140,
      "text_height": 16,
      "text_align": "left"
    },
    {
      "type": "shape",
      "id": "tablo_baslik_bg",
      "x": 10,
      "y": 165,
      "width": 400,
      "height": 25,
      "fill_color": "#343a40"
    },
    {
      "type": "text",
      "id": "th_urun",
      "x": 15,
      "y": 170,
      "text": "Ürün",
      "font_family": "Tahoma",
      "font_size": 10,
      "font_bold": true,
      "color": "#ffffff",
      "text_width": 140,
      "text_height": 16,
      "text_align": "left"
    },
    {
      "type": "text",
      "id": "th_adet",
      "x": 160,
      "y": 170,
      "text": "Adet",
      "font_family": "Tahoma",
      "font_size": 10,
      "font_bold": true,
      "color": "#ffffff",
      "text_width": 50,
      "text_height": 16,
      "text_align": "center"
    },
    {
      "type": "text",
      "id": "th_fiyat",
      "x": 215,
      "y": 170,
      "text": "Fiyat",
      "font_family": "Tahoma",
      "font_size": 10,
      "font_bold": true,
      "color": "#ffffff",
      "text_width": 60,
      "text_height": 16,
      "text_align": "right"
    },
    {
      "type": "text",
      "id": "th_iskonto",
      "x": 280,
      "y": 170,
      "text": "İskonto",
      "font_family": "Tahoma",
      "font_size": 10,
      "font_bold": true,
      "color": "#ffffff",
      "text_width": 55,
      "text_height": 16,
      "text_align": "center"
    },
    {
      "type": "text",
      "id": "th_toplam",
      "x": 340,
      "y": 170,
      "text": "Toplam",
      "font_family": "Tahoma",
      "font_size": 10,
      "font_bold": true,
      "color": "#ffffff",
      "text_width": 65,
      "text_height": 16,
      "text_align": "right"
    },
    {
      "type": "text",
      "id": "row_urun",
      "x": 15,
      "y": 195,
      "text": "{{URUN_ADI}}",
      "font_family": "Tahoma",
      "font_size": 10,
      "font_bold": false,
      "color": "#000000",
      "text_width": 140,
      "text_height": 16,
      "text_align": "left",
      "is_product_row": true
    },
    {
      "type": "text",
      "id": "row_adet",
      "x": 160,
      "y": 195,
      "text": "{{MIKTAR}}",
      "font_family": "Tahoma",
      "font_size": 10,
      "font_bold": false,
      "color": "#000000",
      "text_width": 50,
      "text_height": 16,
      "text_align": "center",
      "is_product_row": true
    },
    {
      "type": "text",
      "id": "row_fiyat",
      "x": 215,
      "y": 195,
      "text": "{{FIYAT}} TL",
      "font_family": "Tahoma",
      "font_size": 10,
      "font_bold": false,
      "color": "#000000",
      "text_width": 60,
      "text_height": 16,
      "text_align": "right",
      "is_product_row": true
    },
    {
      "type": "text",
      "id": "row_iskonto",
      "x": 280,
      "y": 195,
      "text": "%{{ISKONTO}}",
      "font_family": "Tahoma",
      "font_size": 10,
      "font_bold": false,
      "color": "#000000",
      "text_width": 55,
      "text_height": 16,
      "text_align": "center",
      "is_product_row": true
    },
    {
      "type": "text",
      "id": "row_toplam",
      "x": 340,
      "y": 195,
      "text": "{{SATIR_TOPLAM}} TL",
      "font_family": "Tahoma",
      "font_size": 10,
      "font_bold": false,
      "color": "#000000",
      "text_width": 65,
      "text_height": 16,
      "text_align": "right",
      "is_product_row": true
    },
    {
      "type": "shape",
      "id": "row_line",
      "x": 10,
      "y": 213,
      "width": 400,
      "height": 1,
      "fill_color": "#e0e0e0",
      "is_product_row": true
    },
    {
      "type": "shape",
      "id": "total_bg",
      "x": 200,
      "y": 280,
      "width": 210,
      "height": 32,
      "fill_color": "#343a40",
      "is_dynamic_footer": true
    },
    {
      "type": "text",
      "id": "genel_toplam_label",
      "x": 210,
      "y": 287,
      "text": "Toplam:",
      "font_family": "Tahoma",
      "font_size": 12,
      "font_bold": true,
      "color": "#ffffff",
      "text_width": 80,
      "text_height": 18,
      "text_align": "left",
      "is_dynamic_footer": true
    },
    {
      "type": "text",
      "id": "genel_toplam_value",
      "x": 300,
      "y": 287,
      "text": "{{GENEL_TOPLAM}} TL",
      "font_family": "Tahoma",
      "font_size": 14,
      "font_bold": true,
      "color": "#ffffff",
      "text_width": 100,
      "text_height": 18,
      "text_align": "right",
      "is_dynamic_footer": true
    },
    {
      "type": "shape",
      "id": "balance_bg",
      "x": 10,
      "y": 322,
      "width": 400,
      "height": 50,
      "fill_color": "#f9f9f9",
      "border": {
        "sides": {
          "top": true,
          "bottom": true,
          "left": true,
          "right": true
        },
        "thickness": 1,
        "color": "#ddd"
      },
      "is_dynamic_footer": true
    },
    {
      "type": "text",
      "id": "eski_bakiye",
      "x": 20,
      "y": 330,
      "text": "Önceki Bakiye: {{ESKI_BAKIYE}} TL",
      "font_family": "Tahoma",
      "font_size": 10,
      "font_bold": false,
      "color": "#666666",
      "text_width": 380,
      "text_height": 16,
      "text_align": "left",
      "is_dynamic_footer": true
    },
    {
      "type": "text",
      "id": "yeni_bakiye",
      "x": 20,
      "y": 350,
      "text": "Güncel Bakiye: {{YENI_BAKIYE}} TL",
      "font_family": "Tahoma",
      "font_size": 12,
      "font_bold": true,
      "color": "#000000",
      "text_width": 380,
      "text_height": 18,
      "text_align": "left",
      "is_dynamic_footer": true
    },
    {
      "type": "text",
      "id": "footer_msg",
      "x": 10,
      "y": 390,
      "text": "Bizi tercih ettiğiniz için teşekkür ederiz.",
      "font_family": "Tahoma",
      "font_size": 10,
      "font_bold": false,
      "color": "#666666",
      "text_width": 400,
      "text_height": 16,
      "text_align": "center",
      "is_dynamic_footer": true
    }
  ]
}